Metadata-Version: 1.1
Name: NetfilterQueue
Version: 0.9.0
Summary: Python bindings for libnetfilter_queue
Home-page: https://github.com/oremanj/python-netfilterqueue
Author: Matthew Fox
Author-email: matt@tansen.ca
License: MIT
Platform: UNKNOWN
Classifier: Development Status :: 5 - Production/Stable
Classifier: License :: OSI Approved :: MIT License
Classifier: Operating System :: POSIX :: Linux
Classifier: Topic :: System :: Networking
Classifier: Topic :: Security
Classifier: Intended Audience :: Developers
Classifier: Intended Audience :: Telecommunications Industry
Classifier: Programming Language :: Cython
Classifier: Programming Language :: Python :: 2
Classifier: Programming Language :: Python :: 3
